setup.cfg
setup.py
mobify/__init__.py
mobify/cli.py
mobify/errors.py
mobify/publisher.py
mobify/source.py
mobify/version.py
mobify.egg-info/PKG-INFO
mobify.egg-info/SOURCES.txt
mobify.egg-info/dependency_links.txt
mobify.egg-info/entry_points.txt
mobify.egg-info/requires.txt
mobify.egg-info/top_level.txt
mobify/sources/__init__.py
mobify/sources/histmag.py
mobify/test/__init__.py
mobify/test/test_histmag.py
mobify/test/test_publisher.py