Metadata-Version: 1.1
Name: mobify
Version: 0.1.0
Summary: Download a webpage as an e-book
Home-page: https://github.com/macbre/mobify
Author: Maciej Brencz
Author-email: maciej.brencz@gmail.com
License: UNKNOWN
Keywords: epub mobi ebook html converter
Platform: UNKNOWN
Classifier: Environment :: Console
Classifier: Programming Language :: Python :: 2
Classifier: Programming Language :: Python :: 2.7
Classifier: Programming Language :: Python :: 3
Classifier: Programming Language :: Python :: 3.3
Classifier: Programming Language :: Python :: 3.4
